SmileDB/SmileDB.py
SmileDB/__init__.py
SmileDB-0.2.0.dist-info/LICENSE
SmileDB-0.2.0.dist-info/METADATA
SmileDB-0.2.0.dist-info/WHEEL
SmileDB-0.2.0.dist-info/top_level.txt
SmileDB-0.2.0.dist-info/RECORD
