Metadata-Version: 2.1
Name: SmileDB
Version: 0.2.0
Summary: SmileDB is a library built on sqlite3 to make working with databases easier
Home-page: https://github.com/amr2018/SmileDB
Author: Free Python Code
Author-email: amr.ee@yahoo.com
License: MIT
Classifier: License :: OSI Approved :: MIT License
Classifier: Programming Language :: Python
Classifier: Programming Language :: Python :: 3
Classifier: Programming Language :: Python :: 3.6
Classifier: Programming Language :: Python :: Implementation :: CPython
Classifier: Programming Language :: Python :: Implementation :: PyPy
Requires-Python: >=3.1.0
License-File: LICENSE
Requires-Dist: bcrypt
Requires-Dist: html
